pyfastlru/__init__.py
pyfastlru/lru_cache.py
pyfastlru/lru_cache_test.py
pyfastlru-1.0.3.dist-info/METADATA
pyfastlru-1.0.3.dist-info/WHEEL
pyfastlru-1.0.3.dist-info/licenses/LICENSE
pyfastlru-1.0.3.dist-info/RECORD
