Metadata-Version: 2.4
Name: pyfastlru
Version: 1.0.3
Summary: Python implementation of a thread-safe LRU cache.
Project-URL: Homepage, https://github.com/AnatoliyProjects/pyfastlru
Project-URL: Issues, https://github.com/AnatoliyProjects/pyfastlru
Author-email: Anatoly Petrov <petrov.projects@gmail.com>
License-Expression: MIT
License-File: LICENSE
Classifier: Operating System :: OS Independent
Classifier: Programming Language :: Python :: 3
Requires-Python: >=3.12
